Metadata-Version: 2.4
Name: graphapproximator
Version: 0.2.0
Summary: toolkit to find the approximate function of a graph
Author-email: deftasparagusanaconda <deftasparagusanaconda@gmail.com>, Jeffrin Santon <jeffrinsanton0909@gmail.com>
License-Expression: GPL-3.0-or-later
Project-URL: Homepage, https://github.com/deftasparagusanaconda/graphapproximator
Project-URL: Issues, https://github.com/deftasparagusanaconda/graphapproximator/issues
Project-URL: Documentation, https://github.com/deftasparagusanaconda/graphapproximator/documentation
Project-URL: Repository, https://github.com/deftasparagusanaconda/graphapproximator
Keywords: graph,model,curve,line,parabola,expression,approximation,symbolic,regression,regress,optimization,optimize,iterative,plot
Classifier: Programming Language :: Python :: 3.13
Requires-Python: >=3.13.2
License-File: LICENSE
Requires-Dist: numpy
Requires-Dist: matplotlib
Provides-Extra: fft
Requires-Dist: scipy; extra == "fft"
Dynamic: license-file
